ayanna/__init__.py
ayanna-0.0.1.dist-info/METADATA
ayanna-0.0.1.dist-info/WHEEL
ayanna-0.0.1.dist-info/top_level.txt
ayanna-0.0.1.dist-info/RECORD
