Metadata-Version: 2.4
Name: ayanna
Version: 0.0.1
Summary: Dummy lock package for ayanna
Author: AutoPublisher
